hcaptcha/__init__.py
hcaptcha/apps.py
hcaptcha/fields.py
hcaptcha/settings.py
hcaptcha/views.py
hcaptcha/widgets.py
hcaptcha/migrations/__init__.py
hcaptcha/templates/hcaptcha_widget.html
django_110_hCaptcha-1.0.5.dist-info/LICENSE
django_110_hCaptcha-1.0.5.dist-info/METADATA
django_110_hCaptcha-1.0.5.dist-info/WHEEL
django_110_hCaptcha-1.0.5.dist-info/top_level.txt
django_110_hCaptcha-1.0.5.dist-info/RECORD
