Metadata-Version: 2.1
Name: django-110-hCaptcha
Version: 1.0.5
Summary: Django-110-hCaptcha provides a simple way to protect your django 1.10 forms using hCaptcha
Home-page: https://github.com/mzulqarnain1
Author: M. Zulqarnain
Author-email: zulqarnain.mailbox@gmail.com
License: BSD-3-Clause
Platform: UNKNOWN
Classifier: Environment :: Web Environment
Classifier: Framework :: Django
Classifier: Framework :: Django :: 1.10
Classifier: Intended Audience :: Developers
Classifier: License :: OSI Approved :: BSD License
Classifier: Operating System :: OS Independent
Classifier: Programming Language :: Python
Classifier: Programming Language :: Python :: 3
Classifier: Programming Language :: Python :: 3 :: Only
Classifier: Programming Language :: Python :: 3.6
Classifier: Programming Language :: Python :: 3.7
Classifier: Programming Language :: Python :: 3.8
Classifier: Topic :: Internet :: WWW/HTTP
Classifier: Topic :: Internet :: WWW/HTTP :: Dynamic Content
